atbu/common/__init__.py
atbu/common/aes_cbc.py
atbu/common/exception.py
atbu/common/hasher.py
atbu/common/multi_json_enc_dec.py
atbu/common/process_file_lock.py
atbu/common/profile.py
atbu/common/simple_report.py
atbu/common/singleton.py
atbu/common/util_helpers.py
atbu_common_pkg-0.0.12.dist-info/LICENSE
atbu_common_pkg-0.0.12.dist-info/METADATA
atbu_common_pkg-0.0.12.dist-info/WHEEL
atbu_common_pkg-0.0.12.dist-info/top_level.txt
atbu_common_pkg-0.0.12.dist-info/RECORD
