Metadata-Version: 2.1
Name: atbu-common-pkg
Version: 0.0.12
Summary: ATBU common package, common modules used by atbu.backup and atbu.mp_pipeline.
Home-page: https://github.com/AshleyT3/atbu-common
Author: Ashley R. Thomas
Author-email: ashley.r.thomas.701@gmail.com
Project-URL: Bug Tracker, https://github.com/AshleyT3/atbu-common/issues
Classifier: Programming Language :: Python :: 3
Classifier: Programming Language :: Python :: 3.10
Classifier: Programming Language :: Python :: 3.11
Classifier: Programming Language :: Python :: 3.12
Classifier: License :: OSI Approved :: Apache Software License
Classifier: Operating System :: OS Independent
Classifier: Topic :: Security :: Cryptography
Requires-Python: >=3.10
License-File: LICENSE
Requires-Dist: cryptography>=43.0.0
